cqarchaeo/__init__.py
cqarchaeo/cqarchaeo.py
cqarchaeo-0.0.6.dist-info/LICENSE
cqarchaeo-0.0.6.dist-info/METADATA
cqarchaeo-0.0.6.dist-info/WHEEL
cqarchaeo-0.0.6.dist-info/top_level.txt
cqarchaeo-0.0.6.dist-info/RECORD
