Metadata-Version: 2.1
Name: cqarchaeo
Version: 0.0.6
Summary: A simple package to analyze archaeological data using Quantogram analysis
Home-page: https://github.com/lrncrd/CQArchaeo
Author: Lorenzo Cardarelli
Author-email: Lorenzo Cardarelli <lorenzocardarelli2@gmail.com>
Requires-Python: >=3.9
License-File: LICENSE
Requires-Dist: pandas
Requires-Dist: matplotlib
Requires-Dist: numpy
Requires-Dist: seaborn
Requires-Dist: tqdm
Requires-Dist: openpyxl
